archimedes_config/__init__.py
archimedes_config/arckeyl.py
archimedes_config/config_manager.py
archimedes_config/exceptions.py
archimedes_config/keyvault_client.py
archimedes_config/keyvault_config_manager.py
archimedes_config/utils/path_utils.py
archimedes_config/utils/util.py
archimedes_config/workflows/add_secrets.py
archimedes_config/workflows/extract_secret.py
archimedes_config/workflows/lock_secrets.py
archimedes_config/workflows/secret_creation.py
archimedes_config/workflows/unlock_secrets.py
archimedes_config/workflows/workflow_base.py
archimedes_config-0.3.7.dist-info/METADATA
archimedes_config-0.3.7.dist-info/WHEEL
archimedes_config-0.3.7.dist-info/entry_points.txt
archimedes_config-0.3.7.dist-info/RECORD
