Metadata-Version: 2.1
Name: archimedes-config
Version: 0.3.7
Summary: 
Author: BigyaPradhan
Author-email: bigya.pradhan@optimeering.com
Requires-Python: >=3.8.0,<3.12
Classifier: Programming Language :: Python :: 3
Classifier: Programming Language :: Python :: 3.8
Classifier: Programming Language :: Python :: 3.9
Classifier: Programming Language :: Python :: 3.10
Classifier: Programming Language :: Python :: 3.11
Provides-Extra: azure-keyvault
Requires-Dist: azure-identity ; extra == "azure-keyvault"
Requires-Dist: azure-keyvault-secrets ; extra == "azure-keyvault"
Requires-Dist: click (>=8.1.3,<9.0.0)
Requires-Dist: cryptography (>=41.0.0,<42.0.0)
Requires-Dist: tomlkit (>=0.11.6,<0.12.0)
